hydra_kernel/__init__.py
hydra_kernel/__main__.py
hydra_kernel/binding.py
hydra_kernel/exception.py
hydra_kernel/install.py
hydra_kernel/kernel.py
hydra_kernel/kernelspec.py
hydra_kernel/magics.py
hydra_kernel/manager.py
hydra_kernel/traitlets.py
hydra_kernel/utils.py
hydra_kernel/provisioning/__init__.py
hydra_kernel/provisioning/base.py
hydra_kernel/provisioning/local.py
hydra_kernel/provisioning/ssh.py
hydra_kernel/provisioning/zun.py
jupyterlab_chameleon/__init__.py
jupyterlab_chameleon/_version.py
jupyterlab_chameleon/artifact.py
jupyterlab_chameleon/db.py
jupyterlab_chameleon/db_schema.sql
jupyterlab_chameleon/exception.py
jupyterlab_chameleon/heartbeat.py
jupyterlab_chameleon/test_db.py
jupyterlab_chameleon/trovi.py
jupyterlab_chameleon/util.py
jupyterlab_chameleon/extensions/__init__.py
jupyterlab_chameleon/extensions/bash_kernel.py
jupyterlab_chameleon/labextension/package.json
jupyterlab_chameleon/labextension/schemas/@chameleoncloud/jupyterlab-chameleon/artifact-sharing.json
jupyterlab_chameleon/labextension/schemas/@chameleoncloud/jupyterlab-chameleon/cell-binding.json
jupyterlab_chameleon/labextension/schemas/@chameleoncloud/jupyterlab-chameleon/package.json.orig
jupyterlab_chameleon/labextension/static/352.3b0cc2432258fa776884.js
jupyterlab_chameleon/labextension/static/500.6dc52072aa78be58fa55.js
jupyterlab_chameleon/labextension/static/539.af097ce3a5e6164d972e.js
jupyterlab_chameleon/labextension/static/539.af097ce3a5e6164d972e.js.LICENSE.txt
jupyterlab_chameleon/labextension/static/remoteEntry.f489691972ba81cb0309.js
jupyterlab_chameleon/labextension/static/style.js
jupyterlab_chameleon/labextension/static/third-party-licenses.json
jupyterlab_chameleon-3.0.14.data/data/bin/hydra-agent
jupyterlab_chameleon-3.0.14.data/data/bin/hydra-subkernel
jupyterlab_chameleon-3.0.14.data/data/etc/jupyter/jupyter_notebook_config.d/jupyterlab-chameleon.json
jupyterlab_chameleon-3.0.14.data/data/etc/jupyter/jupyter_server_config.d/jupyterlab-chameleon.json
jupyterlab_chameleon-3.0.14.dist-info/LICENSE
jupyterlab_chameleon-3.0.14.dist-info/METADATA
jupyterlab_chameleon-3.0.14.dist-info/WHEEL
jupyterlab_chameleon-3.0.14.dist-info/entry_points.txt
jupyterlab_chameleon-3.0.14.dist-info/top_level.txt
jupyterlab_chameleon-3.0.14.dist-info/RECORD
